c6t/__init__.py
c6t/__main__.py
c6t/cli.py
c6t/api/__init__.py
c6t/api/agent_config.py
c6t/api/applications.py
c6t/api/maven_repo.py
c6t/configure/__init__.py
c6t/configure/credentials.py
c6t/external/__init__.py
c6t/external/integrations/scw/__init__.py
c6t/external/integrations/scw/contrast_api.py
c6t/external/integrations/scw/contrast_scw.py
c6t/templates/contrast_security.yaml.j2
c6t/templates/contrast_security_env.yaml.j2
c6t/tools/__init__.py
c6t/tools/send_udp_test_message.py
c6t/tools/udp_server.py
c6t/ui/auth.py
c6t-0.2.0.dist-info/METADATA
c6t-0.2.0.dist-info/WHEEL
c6t-0.2.0.dist-info/entry_points.txt
c6t-0.2.0.dist-info/licenses/LICENSE
c6t-0.2.0.dist-info/RECORD
