Metadata-Version: 2.3
Name: c6t
Version: 0.2.0
Summary: Unofficial Administrative Command Line Interface for Contrast Security
Project-URL: Homepage, https://github.com/jharper-sec/c6t
Project-URL: Issues, https://github.com/jharper-sec/c6t/issues
Project-URL: Documentation, https://github.com/jharper-sec/c6t/blob/main/README.md
Author-email: Jonathan Harper <39912347+jharper-sec@users.noreply.github.com>
License:                                  Apache License
Classifier: License :: OSI Approved :: Apache Software License
Classifier: Operating System :: OS Independent
Classifier: Programming Language :: Python :: 3
Requires-Python: >=3.8
Requires-Dist: gitpython>=3.1.43
Requires-Dist: httpx>=0.27.0
Requires-Dist: jinja2>=3.1.4
Requires-Dist: lxml>=5.2.2
Requires-Dist: pyyaml>=6.0.1
Requires-Dist: questionary>=2.0.1
Requires-Dist: rich>=13.7.1
Requires-Dist: typer>=0.12.3
Requires-Dist: types-pyyaml>=6.0.12.20240311
